sgtree/__init__.py
sgtree/sgtree.py
sgtree-0.0.10.dist-info/LICENSE.txt
sgtree-0.0.10.dist-info/METADATA
sgtree-0.0.10.dist-info/WHEEL
sgtree-0.0.10.dist-info/entry_points.txt
sgtree-0.0.10.dist-info/top_level.txt
sgtree-0.0.10.dist-info/RECORD
