Metadata-Version: 2.1
Name: sgtree
Version: 0.0.10
Summary: Computational pipeline for fast and easy construction of phylogenetic trees.
Home-page: https://bitbucket.org/ewanjameswhittakerwalker/sgtree
Author: Frederik Schulz, Ewan Whittaker Walker, Sean Jungbluth
License: Modified BSD
Keywords: bioinformatics,genomics,metagenomics,phylogenetics
Platform: UNKNOWN
Classifier: Intended Audience :: Science/Research
Classifier: Natural Language :: English
Classifier: Topic :: Software Development :: Libraries
Classifier: Topic :: Scientific/Engineering :: Bio-Informatics
Classifier: License :: OSI Approved :: BSD License
Classifier: Programming Language :: Python :: 3
Requires-Python: >=3.7
Requires-Dist: setuptools
Requires-Dist: numpy
Requires-Dist: pandas
Requires-Dist: importlib-metadata (>=0.12) ; python_version < "3.8"
